NEMO_reports/__init__.py
NEMO_reports/app_settings.py
NEMO_reports/apps.py
NEMO_reports/customizations.py
NEMO_reports/models.py
NEMO_reports/urls.py
NEMO_reports/migrations/0001_initial.py
NEMO_reports/migrations/0002_alter_report_options.py
NEMO_reports/migrations/__init__.py
NEMO_reports/static/NEMO_reports/NEMO_reports.css
NEMO_reports/static/NEMO_reports/daterangepicker.css
NEMO_reports/static/NEMO_reports/daterangepicker.js
NEMO_reports/templates/NEMO_reports/report_active_users.html
NEMO_reports/templates/NEMO_reports/report_base.html
NEMO_reports/templates/NEMO_reports/report_facility_usage.html
NEMO_reports/templates/NEMO_reports/report_new_users.html
NEMO_reports/templates/NEMO_reports/report_project_listing.html
NEMO_reports/templates/NEMO_reports/report_project_users.html
NEMO_reports/templates/NEMO_reports/reports.html
NEMO_reports/templates/base/navbar.html
NEMO_reports/templates/base/navbar_reports.html
NEMO_reports/templates/customizations/customizations_reports.html
NEMO_reports/templatetags/__init__.py
NEMO_reports/templatetags/reports_tags.py
NEMO_reports/tests/__init__.py
NEMO_reports/tests/test_settings.py
NEMO_reports/tests/test_settings_with_billing.py
NEMO_reports/tests/test_utilities.py
NEMO_reports/tests/test_reports/__init__.py
NEMO_reports/tests/test_reports/test_reports.py
NEMO_reports/views/__init__.py
NEMO_reports/views/reporting.py
NEMO_reports/views/reporting_facilily_usage.py
NEMO_reports/views/reporting_invoice_charges.py
NEMO_reports/views/reporting_invoice_item_charges.py
NEMO_reports/views/reporting_new_user_activities.py
NEMO_reports/views/reporting_project_listing.py
NEMO_reports/views/reporting_project_users.py
NEMO_reports/views/reporting_unique_user_prj_acc.py
nemo_reports-2.1.10.dist-info/licenses/LICENSE
nemo_reports-2.1.10.dist-info/METADATA
nemo_reports-2.1.10.dist-info/WHEEL
nemo_reports-2.1.10.dist-info/top_level.txt
nemo_reports-2.1.10.dist-info/RECORD
